dingpy
