Metadata-Version: 2.1
Name: dingpy
Version: 1.0.4
Summary: added list_alarms local vs s3 mode; cleaned setup.py
Home-page: https://github.com/tinahbu/dingpy
Author: Tina Bu
Author-email: tina.hongbu@gmail.com
License: MIT license
Keywords: notification,alarm,alert
Platform: UNKNOWN
Classifier: Programming Language :: Python :: 3
Classifier: Programming Language :: Python :: 3.4
Classifier: Programming Language :: Python :: 3.5
Classifier: Programming Language :: Python :: 3.6
Classifier: Programming Language :: Python :: 3.7
Classifier: Programming Language :: Python :: 3.8
Classifier: License :: OSI Approved :: MIT License
Classifier: Operating System :: OS Independent
Classifier: Intended Audience :: Developers
